Metadata-Version: 2.1
Name: examplepython
Version: 0.1
Summary: Módulo teste para PyTools
Home-page: https://github.com/victorsmorais/examplepython
Author: Victor Morais
Author-email: victorsanmorais@gmail.com
License: GNU AFFERO GENERAL PUBLIC LICENSE
Platform: UNKNOWN
Classifier: Development Status :: 2 - Pre-Alpha
Classifier: Environment :: Console
Classifier: Intended Audience :: Developers
Classifier: License :: OSI Approved :: GNU Affero General Public License v3 
Classifier: Operating System :: OS Independent
Classifier: Programming Language :: Python :: 3.9
Classifier: Framework :: Pytest
